__init__.py
client.py
personal_banking_client.py
investec_openapi_wrapper-0.0.2.dist-info/LICENSE
investec_openapi_wrapper-0.0.2.dist-info/METADATA
investec_openapi_wrapper-0.0.2.dist-info/WHEEL
investec_openapi_wrapper-0.0.2.dist-info/top_level.txt
investec_openapi_wrapper-0.0.2.dist-info/RECORD
