Metadata-Version: 2.1
Name: investec-openapi-wrapper
Version: 0.0.2
Summary: Investec Programmable Banking (OpenAPI) wrapper
Author-email: Anri Goosen <aesnyma.n+pypi@gmail.com>
License: The MIT License (MIT)
Project-URL: Homepage, https://github.com/GoosenA/ipb-python-wrapper
Project-URL: Bug Tracker, https://github.com/GoosenA/ipb-python-wrapper/issues
Requires-Python: >=3.7
License-File: LICENSE
Requires-Dist: requests
